d51_deploy/__init__.py
d51_deploy/command_line.py
d51_deploy/deploy.py
d51_deploy-0.6.dist-info/METADATA
d51_deploy-0.6.dist-info/WHEEL
d51_deploy-0.6.dist-info/entry_points.txt
d51_deploy-0.6.dist-info/top_level.txt
d51_deploy-0.6.dist-info/RECORD
